<annotation>
	<folder>tmp</folder>
	<filename>green_51.jpg</filename>
	<path>/Users/yuki/workspace/ai/data-science-projects/driving-object-detection/images/tmp/green_51.jpg</path>
	<source>
		<database>Unknown</database>
	</source>
	<size>
		<width>800</width>
		<height>600</height>
		<depth>3</depth>
	</size>
	<segmented>0</segmented>
	<object>
		<name>green</name>
		<pose>Unspecified</pose>
		<truncated>0</truncated>
		<difficult>0</difficult>
		<bndbox>
			<xmin>38</xmin>
			<ymin>428</ymin>
			<xmax>75</xmax>
			<ymax>501</ymax>
		</bndbox>
	</object>
	<object>
		<name>green</name>
		<pose>Unspecified</pose>
		<truncated>0</truncated>
		<difficult>0</difficult>
		<bndbox>
			<xmin>183</xmin>
			<ymin>432</ymin>
			<xmax>220</xmax>
			<ymax>505</ymax>
		</bndbox>
	</object>
	<object>
		<name>green</name>
		<pose>Unspecified</pose>
		<truncated>0</truncated>
		<difficult>0</difficult>
		<bndbox>
			<xmin>322</xmin>
			<ymin>438</ymin>
			<xmax>359</xmax>
			<ymax>511</ymax>
		</bndbox>
	</object>
</annotation>
